dict2dataclass/__init__.py
dict2dataclass/dict_field.py
dict2dataclass/from_dict.py
dict2dataclass/to_dict.py
dict2dataclass-0.4.0.dist-info/LICENSE
dict2dataclass-0.4.0.dist-info/METADATA
dict2dataclass-0.4.0.dist-info/WHEEL
dict2dataclass-0.4.0.dist-info/RECORD
