Metadata-Version: 2.3
Name: dict2dataclass
Version: 0.4.0
Summary: Convert dicts into dataclasses. Supports lists, dicts and unions.
License: Apache-2.0
Author: Nathanael DEMACON
Author-email: quantumsheep@users.noreply.github.com
Requires-Python: >=3.9,<4.0
Classifier: Development Status :: 3 - Alpha
Classifier: Environment :: Console
Classifier: Intended Audience :: Developers
Classifier: License :: OSI Approved :: Apache Software License
Classifier: Operating System :: OS Independent
Classifier: Programming Language :: Python :: 3
Classifier: Programming Language :: Python :: 3.9
Classifier: Programming Language :: Python :: 3.10
Classifier: Programming Language :: Python :: 3.11
Classifier: Programming Language :: Python :: 3.12
Classifier: Programming Language :: Python :: 3.13
Classifier: Topic :: Software Development
Project-URL: Homepage, https://github.com/quantumsheep/dict2dataclass
